finarith_guard/__init__.py
finarith_guard/detector.py
finarith_guard/exceptions.py
finarith_guard/guard.py
finarith_guard/policy.py
testing/testing.py
tests/init.py
tests/test_division.py
tests/test_float_precision.py
tests/test_float_risk.py
tests/test_pipeline_simulation.py
tests/test_policy_enforcement.py
tests/test_safe_operations.py
tests/test_stress.py
tests/test_version.py
finarith_guard-0.1.2.dist-info/METADATA
finarith_guard-0.1.2.dist-info/WHEEL
finarith_guard-0.1.2.dist-info/top_level.txt
finarith_guard-0.1.2.dist-info/RECORD
