Metadata-Version: 2.4
Name: finarith-guard
Version: 0.1.2
Summary: Runtime arithmetic safety guard for fintech numeric validation
Author-email: Harshal I <harshal4437@gmail.com>
License: MIT
Requires-Python: >=3.9
